[{"title":"『副業の確定申告はどうしたらいい？』","date":"20200122","link":"https://newspicks.com/news/4564197?ref=search&ref_q=%E5%89%AF%E6%A5%AD&ref_t=top","service":"newspicks","month":"202001","img":"https://contents.newspicks.com/images/news/4564197?updatedAt=20200122111903"},{"service":"hatena","date":"20200122","img":"https://cdn-ak-scissors.b.st-hatena.com/image/square/35636c0c3665f39b913a33a1db7a79202e3423df/height=280;version=1;width=400/https%3A%2F%2Fcdn-ak.f.st-hatena.com%2Fimages%2Ffotolife%2Fh%2Fharudake%2F20200121%2F20200121225038.jpg","month":"202001","title":"【ココナラ】スキルアップができる副業　　『副業のススメ』 - harudakeのブログ","link":"https://harudake.hatenablog.com/entry/2020/01/22/%E3%80%90%E3%82%B3%E3%82%B3%E3%83%8A%E3%83%A9%E3%80%91%E3%82%B9%E3%82%AD%E3%83%AB%E3%82%A2%E3%83%83%E3%83%97%E3%81%8C%E3%81%A7%E3%81%8D%E3%82%8B%E5%89%AF%E6%A5%AD_%E3%80%8E%E5%89%AF%E6%A5%AD%E3%81%AE"},{"service":"note","title":"【完全保存版】 現金取っ払いはバレる？会社にばれずに副業を始める方法！確定申告のやり方も解説","date":"20200122","link":"https://note.com/maihajivest/n/nc5876574450b","img":"https://d2l930y2yx77uc.cloudfront.net/production/uploads/images/18239580/rectangle_large_type_2_241a8eb4f034a80a41c284aeb70d463a.jpeg","month":"202001"},{"img":"https://d2l930y2yx77uc.cloudfront.net/production/uploads/images/18260023/rectangle_large_type_2_28a9292cf9255aa72308e53a15a61247.jpeg","service":"note","link":"https://note.com/aaashitano964/n/nb273cbabf13d","title":"わたしが応援する会社。ネットで副業するならこれいいかも〜f","month":"202001","date":"20200122"},{"month":"202001","date":"20200122","link":"https://newspicks.com/news/4563549?ref=search&ref_q=%E5%89%AF%E6%A5%AD&ref_t=top","service":"newspicks","img":"https://contents.newspicks.com/images/news/4563549?updatedAt=20200122080117","title":"パイロット国王も　公務と「副業」をこなす欧州の王族たち"},{"service":"note","month":"202001","link":"https://note.com/kawasawa100/n/n94adbed7c12b","title":"一般公開開始です！［副業ファミリーオンラインサロン］","date":"20200122","img":"https://d2l930y2yx77uc.cloudfront.net/production/uploads/images/18243105/rectangle_large_type_2_9b71d567f360c08d8689c8f49a3549a0.png"},{"date":"20200122","link":"https://note.com/workaslife_2020/n/n13c704961ea6","title":"仕事が志事であるように、副業が福業であるように","service":"note","month":"202001","img":""},{"date":"20200122","img":"https://contents.newspicks.com/images/news/4562165?updatedAt=20200122002811","title":"働き方改革に取り組んでいる企業、前回の調査より22.9%増。今後の注目となる施策はテレワークや副業 - オフィスのミカタ","month":"202001","link":"https://newspicks.com/news/4562165?ref=search&ref_q=%E5%89%AF%E6%A5%AD&ref_t=top","service":"newspicks"},{"link":"https://note.com/satosh_i_sugar/n/n0197b46982cc","date":"20200122","title":"副業、ブログ【孤独な作業】をひとりで頑張るには","img":"https://d2l930y2yx77uc.cloudfront.net/production/uploads/images/18254752/rectangle_large_type_2_438b423d8372e6fd21bde09f9ecd0e13.jpeg","month":"202001","service":"note"},{"img":"","title":"副業として始めるFX","month":"202001","link":"https://note.com/s_kun_fx/n/n46c9b987de91","date":"20200122","service":"note"},{"title":"副業として始めるなら知っておくべきYouTuberの収入の仕組み ヒット作品に学ぶテクニックも紹介 マネリー | お金にまつわる情報メディア","month":"202001","link":"https://moneliy.jp/life/kyuyo/18165","img":"https://cdn-ak-scissors.b.st-hatena.com/image/square/11dcd3fbe261df04e39838c1a863410cceaa168e/height=280;version=1;width=400/https%3A%2F%2Fd17fiusnmlxdvr.cloudfront.net%2Fwp-content%2Fuploads%2F2020%2F01%2F22005150%2FiStock-1132090399-1024x684.jpg","date":"20200122","service":"hatena"},{"title":"大学生時代の副業","month":"202001","img":"https://d2l930y2yx77uc.cloudfront.net/production/uploads/images/18266481/rectangle_large_type_2_87beecd87780138cf2a54a7f4dc46aa6.jpeg","date":"20200122","service":"note","link":"https://note.com/baseballaqua/n/n86fbfc1640fe"},{"img":"","link":"https://note.com/deimannsyuuhachi/n/n875efd7356c5","title":"将来の複業と現代の副業","service":"note","date":"20200122","month":"202001"},{"img":"https://contents.newspicks.com/images/news/4564125?updatedAt=20200122105116","title":"広島在住のエンジニアが語る、フルリモート＋副業という働き方","service":"newspicks","link":"https://newspicks.com/news/4564125?ref=search&ref_q=%E5%89%AF%E6%A5%AD&ref_t=top","date":"20200122","month":"202001"},{"img":"https://cdn-ak-scissors.b.st-hatena.com/image/square/c47148e1cfd2242483e79f6ab50d35518fb41dc8/height=280;version=1;width=400/https%3A%2F%2Fcdn-ak.f.st-hatena.com%2Fimages%2Ffotolife%2Fa%2Fasologu%2F20200122%2F20200122113517.jpg","date":"20200122","month":"202001","link":"https://www.aologu.com/entry/%E5%89%AF%E6%A5%AD","title":"従業員から副業の相談をうけました - 人事ばたけ","service":"hatena"}]